{
	"class" : {
		 },
	"instance" : {
		"endOffset" : "mt 12/9/2017 11:34",
		"evaluateFinishBlock" : "mt 12/9/2017 11:12",
		"evaluateStartBlock" : "mt 12/9/2017 11:13",
		"isGraphicsAnimation" : "mt 5/14/2010 19:32:07.36",
		"isValid" : "mt 12/9/2017 13:00",
		"morph" : "mt 6/16/2010 11:54:53.963",
		"morph:" : "mt 6/16/2010 12:04:40.875",
		"printOn:" : "mt 12/9/2017 09:45",
		"repaint" : "mt 12/8/2017 14:14",
		"resume" : "mt 5/15/2010 18:16:21.399",
		"start" : "mt 11/18/2017 10:08",
		"startOffset" : "mt 12/9/2017 11:34",
		"toEnd" : "mt 11/18/2017 10:08",
		"toStart" : "mt 11/18/2017 10:08",
		"transformedCanvas:" : "mt 5/14/2010 18:51:16.154",
		"type" : "mt 5/17/2010 14:21:57.388",
		"updateCurrentValue:" : "mt 5/14/2010 16:49:13.97" } }
